qc/__init__.py
qc/__main__.py
qc/makelibs.py
qclib/__init__.py
qclib/context.py
qclib/error.py
qclib/function.py
qclib/interpreter.py
qclib/library.py
qclib/program.py
qclib/ast/__init__.py
qclib/ast/assign.py
qclib/ast/branch.py
qclib/ast/builtin.py
qclib/ast/decl.py
qclib/ast/generic.py
qclib/ast/marker.py
qclib/ast/operator.py
qclib/ast/value.py
qclib/generate/__init__.py
qclib/generate/compiler.py
qclib/generate/error.py
qclib/generate/parser.py
qclib/generate/syntax.py
test/__init__.py
test/deps.py
test/test_compiler.py
test/test_constants.py
test/test_examples.py
test/test_interpreter.py
test/test_io.py
test/test_lists.py
test/test_objects.py
test/test_parsing.py
test/test_program.py
test/test_stdlib.py
quasicode-0.0.1.dist-info/LICENSE
quasicode-0.0.1.dist-info/METADATA
quasicode-0.0.1.dist-info/WHEEL
quasicode-0.0.1.dist-info/entry_points.txt
quasicode-0.0.1.dist-info/top_level.txt
quasicode-0.0.1.dist-info/RECORD
